lyric_js_worker/__init__.py
lyric_js_worker/javascript_worker.wasm
lyric_js_worker-0.1.7.dist-info/METADATA
lyric_js_worker-0.1.7.dist-info/WHEEL
lyric_js_worker-0.1.7.dist-info/RECORD
